CHANGES.txt
CONTRIBUTORS.txt
MANIFEST.in
README.txt
setup.cfg
setup.py
docs/LICENSE.GPL
docs/LICENSE.txt
src/ityou/__init__.py
src/ityou.qrcode.egg-info/PKG-INFO
src/ityou.qrcode.egg-info/SOURCES.txt
src/ityou.qrcode.egg-info/dependency_links.txt
src/ityou.qrcode.egg-info/entry_points.txt
src/ityou.qrcode.egg-info/namespace_packages.txt
src/ityou.qrcode.egg-info/not-zip-safe
src/ityou.qrcode.egg-info/paster_plugins.txt
src/ityou.qrcode.egg-info/requires.txt
src/ityou.qrcode.egg-info/top_level.txt
src/ityou/qrcode/PyQRNative.py
src/ityou/qrcode/__init__.py
src/ityou/qrcode/testing.py
src/ityou/qrcode/utils.py
src/ityou/qrcode/browser/__init__.py
src/ityou/qrcode/interfaces/__init__.py
src/ityou/qrcode/interfaces/ityouqrcodelayer.py
src/ityou/qrcode/portlets/__init__.py
src/ityou/qrcode/portlets/qrcode.py
src/ityou/qrcode/tests/__init__.py
src/ityou/qrcode/tests/test_example.py
src/ityou/qrcode/tests/test_robot.py